{
  "resourceType": "databases/oracle",
  "id": "1e6bd48d-e4eb-4272-b260-9cae64337380",
  "displayName": "Ensure the 'CREATE PROCEDURE/FUNCTION/PACKAGE/PACKAGE BODY' Action Audit Is Enabled",
  "severity": "medium",
  "source": "oracle-benchmark",
  "category": "DB",
  "rationale": "Logging and monitoring of all attempts to create procedures, functions, packages or package bodies, whether successful or unsuccessful, may provide clues and forensic evidence about potential suspicious/unauthorized activities. Any such activities may be a cause for further investigation. In addition, organization security policies and industry/government regulations may require logging of all user activities involving creation of procedures, functions, packages or package bodies.",
  "recommended_action": "Execute the following SQL statement to remediate this setting.\n```\nALTER AUDIT POLICY CIS_UNIFIED_AUDIT_POLICY\nADD\nACTIONS\nCREATE PROCEDURE,\nCREATE FUNCTION,\nCREATE PACKAGE,\nCREATE PACKAGE BODY;\n```\n**Note:** If you do not have `CIS_UNIFIED_AUDIT_POLICY`, please create one using the `CREATE AUDIT POLICY` statement.",
  "error_message": "'CREATE PRODECURE/FUNCTION/PACKAGE/PACKAGE BODY' audit option is not enabled",
  "subcategory": "",
  "ruleNames": [
    "Ensure the 'CREATE PROCEDURE/FUNCTION/PACKAGE/PACKAGE BODY' Action Audit Is Enabled"
  ]
}